fastapi_testing/__init__.py
fastapi_testing/async_fastapi_testing.py
fastapi_testing-0.3.2.dist-info/METADATA
fastapi_testing-0.3.2.dist-info/WHEEL
fastapi_testing-0.3.2.dist-info/licenses/LICENSE
fastapi_testing-0.3.2.dist-info/RECORD
