Metadata-Version: 2.4
Name: fastapi-testing
Version: 0.3.2
Summary: A lightweight, async-first testing framework for FastAPI applications
Project-URL: Homepage, https://github.com/descoped/fastapi-testing
Project-URL: Repository, https://github.com/descoped/fastapi-testing
Project-URL: Issues, https://github.com/descoped/fastapi-testing/issues
Author-email: Ove Ranheim <oranheim@gmail.com>
License: MIT
License-File: LICENSE
Keywords: async,fastapi,integration-testing,pytest,test-framework,testing
Classifier: Development Status :: 5 - Production/Stable
Classifier: Framework :: FastAPI
Classifier: Intended Audience :: Developers
Classifier: License :: OSI Approved :: MIT License
Classifier: Operating System :: OS Independent
Classifier: Programming Language :: Python :: 3
Classifier: Programming Language :: Python :: 3.11
Classifier: Programming Language :: Python :: 3.12
Classifier: Programming Language :: Python :: 3.13
Classifier: Topic :: Software Development :: Libraries :: Python Modules
Classifier: Topic :: Software Development :: Testing
Classifier: Typing :: Typed
Requires-Python: >=3.11
Requires-Dist: fastapi>=0.116.1
Requires-Dist: httpx[http2]>=0.28.1
Requires-Dist: starlette>=0.47.2
Requires-Dist: uvicorn>=0.35.0
Requires-Dist: websockets>=15.0.1
